asmek_authcogs/__init__.py
asmek_authcogs/admin.py
asmek_authcogs/app_settings.py
asmek_authcogs/apps.py
asmek_authcogs/auth_hooks.py
asmek_authcogs/models.py
asmek_authcogs/signals.py
asmek_authcogs/Images/__init__.py
asmek_authcogs/Images/eve-o-4.png
asmek_authcogs/Images/smt_bomb_icon-1.png
asmek_authcogs/cogs/__init__.py
asmek_authcogs/cogs/about.py
asmek_authcogs/cogs/auth.py
asmek_authcogs/cogs/hr.py
asmek_authcogs/cogs/links.py
asmek_authcogs/cogs/siege.py
asmek_authcogs/migrations/0001_initial.py
asmek_authcogs/migrations/0002_alter_link_name.py
asmek_authcogs/migrations/0003_alter_general_options.py
asmek_authcogs/migrations/0004_authcogs_delete_general.py
asmek_authcogs/migrations/0005_groupwelcome.py
asmek_authcogs/migrations/0006_remove_groupwelcome_thumbnail.py
asmek_authcogs/migrations/__init__.py
asmek_authcogs-1.3.6.dist-info/METADATA
asmek_authcogs-1.3.6.dist-info/WHEEL
asmek_authcogs-1.3.6.dist-info/licenses/LICENSE
asmek_authcogs-1.3.6.dist-info/RECORD
