Metadata-Version: 2.3
Name: asmek-authcogs
Version: 1.3.6
Project-URL: Documentation, https://github.com/AstrumMechanica/asmek-authcogs#readme
Project-URL: Issues, https://github.com/AstrumMechanica/asmek-authcogs/issues
Project-URL: Source, https://github.com/AstrumMechanica/asmek-authcogs
License-File: LICENSE
Classifier: Programming Language :: Python :: 3 :: Only
Classifier: Programming Language :: Python :: 3.8
Classifier: Programming Language :: Python :: 3.9
Classifier: Programming Language :: Python :: 3.10
Classifier: Programming Language :: Python :: 3.11
Classifier: Programming Language :: Python :: 3.12
Requires-Dist: allianceauth-discordbot
Requires-Dist: allianceauth<5,>=4
